multi_api_mocker/__init__.py
multi_api_mocker/definitions.py
multi_api_mocker/http_utils.py
multi_api_mocker/httpx_utils.py
multi_api_mocker/models.py
multi_api_mocker/contrib/__init__.py
multi_api_mocker/contrib/pytest_plugin.py
multi_api_mocker-1.3.0.dist-info/AUTHORS.md
multi_api_mocker-1.3.0.dist-info/LICENSE
multi_api_mocker-1.3.0.dist-info/METADATA
multi_api_mocker-1.3.0.dist-info/WHEEL
multi_api_mocker-1.3.0.dist-info/entry_points.txt
multi_api_mocker-1.3.0.dist-info/top_level.txt
multi_api_mocker-1.3.0.dist-info/RECORD
