Metadata-Version: 2.2
Name: multi_api_mocker
Version: 1.3.0
Summary: A Python library for generating mock API responses for testing.
Home-page: https://github.com/ottuco/multi_api_mocker
Author: Dacian Popute
Author-email: dacian@ottu.com
License: MIT license
Keywords: multi_api_mocker
Classifier: Development Status :: 5 - Production/Stable
Classifier: Intended Audience :: Developers
Classifier: License :: OSI Approved :: MIT License
Classifier: Natural Language :: English
Classifier: Programming Language :: Python :: 3.8
Classifier: Programming Language :: Python :: 3.9
Classifier: Programming Language :: Python :: 3.10
Requires-Python: >=3.8
License-File: LICENSE
License-File: AUTHORS.md
Provides-Extra: http
Requires-Dist: requests_mock>=1.9.3; extra == "http"
Provides-Extra: httpx
Requires-Dist: pytest-httpx>=0.21.0; extra == "httpx"
Provides-Extra: all
Requires-Dist: requests_mock>=1.9.3; extra == "all"
Requires-Dist: pytest-httpx>=0.21.0; extra == "all"
Dynamic: author
Dynamic: author-email
Dynamic: classifier
Dynamic: description
Dynamic: description-content-type
Dynamic: home-page
Dynamic: keywords
Dynamic: license
Dynamic: provides-extra
Dynamic: requires-python
Dynamic: summary
